{
  "name": "Interest on Debt",
  "currentSpending": 892000000000,
  "currentSpendingRealPerCapita": 2009.11,
  "optimalSpendingPerCapita": null,
  "optimalSpendingNominal": null,
  "gap": 0,
  "gapPercent": 0,
  "recommendation": "maintain",
  "evidenceSource": "non-discretionary (mandated)",
  "outcomeMetrics": [
    {
      "name": "Debt-to-GDP ratio",
      "value": 121,
      "trend": "declining"
    },
    {
      "name": "Net interest as % of revenue",
      "value": 18,
      "trend": "declining"
    },
    {
      "name": "Average interest rate on debt",
      "value": 3.3,
      "trend": "declining"
    }
  ],
  "historicalRealPerCapita": [
    {
      "year": 2015,
      "nominalBillions": 223,
      "realPerCapita": 719.02
    },
    {
      "year": 2016,
      "nominalBillions": 240,
      "realPerCapita": 758.65
    },
    {
      "year": 2017,
      "nominalBillions": 263,
      "realPerCapita": 808.86
    },
    {
      "year": 2018,
      "nominalBillions": 325,
      "realPerCapita": 969.85
    },
    {
      "year": 2019,
      "nominalBillions": 375,
      "realPerCapita": 1094.8
    },
    {
      "year": 2020,
      "nominalBillions": 345,
      "realPerCapita": 985.78
    },
    {
      "year": 2021,
      "nominalBillions": 352,
      "realPerCapita": 958.77
    },
    {
      "year": 2022,
      "nominalBillions": 475,
      "realPerCapita": 1193.42
    },
    {
      "year": 2023,
      "nominalBillions": 659,
      "realPerCapita": 1578.18
    },
    {
      "year": 2024,
      "nominalBillions": 882,
      "realPerCapita": 2038.6
    },
    {
      "year": 2025,
      "nominalBillions": 892,
      "realPerCapita": 2009.11
    }
  ],
  "diminishingReturns": null,
  "efficiency": null,
  "slug": "interest-on-debt",
  "legislationSlug": null,
  "dividendPerAdultYear": 0,
  "dividendPerAdultMonth": 0,
  "isNonDiscretionary": true
}